LICENSE
MANIFEST.in
setup.cfg
setup.py
djangocms_terminal/__init__.py
djangocms_terminal/admin.py
djangocms_terminal/cms_app.py
djangocms_terminal/cms_plugins.py
djangocms_terminal/models.py
djangocms_terminal/tests.py
djangocms_terminal/urls.py
djangocms_terminal/utils.py
djangocms_terminal/views.py
djangocms_terminal.egg-info/PKG-INFO
djangocms_terminal.egg-info/SOURCES.txt
djangocms_terminal.egg-info/dependency_links.txt
djangocms_terminal.egg-info/not-zip-safe
djangocms_terminal.egg-info/pbr.json
djangocms_terminal.egg-info/requires.txt
djangocms_terminal.egg-info/top_level.txt
djangocms_terminal/migrations/__init__.py
djangocms_terminal/static/css/base.css
djangocms_terminal/static/css/terminal-1.0.0.min.css
djangocms_terminal/static/js/common.js
djangocms_terminal/static/js/jquery-2.1.4.min.js
djangocms_terminal/static/js/terminal-1.0.0.min.js
djangocms_terminal/templates/djangocms_terminal/terminal.html
djangocms_terminal/templates/djangocms_terminal/plugins/terminal_plugin.html