Metadata-Version: 1.1
Name: djangocms-terminal
Version: 0.0.11
Summary: Terminal for Django CMS project.
Home-page: https://github.com/fmarco/djangocms-terminal
Author: Marco Federighi
Author-email: federighi.marco@gmail.com
License: MIT
Keywords: terminal,django,debug,djangocms
Platform: OS Independent
Classifier: Development Status :: 2 - Pre-Alpha
Classifier: Environment :: Web Environment
Classifier: Framework :: Django
Classifier: Intended Audience :: Developers
Classifier: License :: OSI Approved :: MIT License
Classifier: Operating System :: OS Independent
Classifier: Programming Language :: Python
Classifier: Topic :: Communications
Classifier: Topic :: Internet :: WWW/HTTP :: Dynamic Content
Classifier: Programming Language :: Python :: 2.7
